setup.py
kg_downloader/__init__.py
kg_downloader/main.py
kg_downloader.egg-info/PKG-INFO
kg_downloader.egg-info/SOURCES.txt
kg_downloader.egg-info/dependency_links.txt
kg_downloader.egg-info/entry_points.txt
kg_downloader.egg-info/not-zip-safe
kg_downloader.egg-info/requires.txt
kg_downloader.egg-info/top_level.txt
kg_downloader/util/__init__.py
kg_downloader/util/api.py
kg_downloader/util/kg_cmder.py