Metadata-Version: 1.1
Name: kg-downloader
Version: 0.2.0
Summary: a python tool which download songs from kg.qq.com.
Home-page: https://github.com/Yaoxuannn/Python_Tools
Author: justin13
Author-email: justin13wyx@gmail.com
License: UNKNOWN
Keywords: python3 terminal downloader
Platform: UNKNOWN
Classifier: Development Status :: 5 - Production/Stable
Classifier: Operating System :: OS Independent
Classifier: Programming Language :: Python :: 3 :: Only
Classifier: Topic :: Terminals
